microbit/Microbit.py
microbit/__init__.py
microbit_3-0.2.dist-info/METADATA
microbit_3-0.2.dist-info/WHEEL
microbit_3-0.2.dist-info/top_level.txt
microbit_3-0.2.dist-info/RECORD
