Metadata-Version: 2.1
Name: microbit-3
Version: 0.2
Summary: Microbit for Python 3
Author: Phoneguytech
License: UNKNOWN
Platform: UNKNOWN
Requires-Dist: pyserial
